README.txt
setup.cfg
setup.py
src/PyACL.egg-info/PKG-INFO
src/PyACL.egg-info/SOURCES.txt
src/PyACL.egg-info/dependency_links.txt
src/PyACL.egg-info/entry_points.txt
src/PyACL.egg-info/namespace_packages.txt
src/PyACL.egg-info/not-zip-safe
src/PyACL.egg-info/top_level.txt
src/acl/__init__.py
src/acl/acls.py
src/acl/aco.py
src/acl/aro.py
src/acl/core.py
src/acl/exc.py
src/acl/adapters/__init__.py
src/acl/adapters/base.py
src/acl/testutils/__init__.py
src/acl/testutils/adapters.py