Metadata-Version: 1.0
Name: PyACL
Version: 1.0a1
Summary: Access Control List (ACL)
Home-page: http://code.gustavonarea.net/pyacl/
Author: Gustavo Narea
Author-email: me@gustavonarea.net
License: GNU Affero General Public License v3 (http://www.gnu.org/licenses/agpl.html)
Keywords: authorization acl acls access control
Platform: UNKNOWN
Classifier: Development Status :: 2 - Pre-Alpha
Classifier: Intended Audience :: Developers
Classifier: License :: OSI Approved :: GNU Affero General Public License v3
Classifier: Natural Language :: English
Classifier: Operating System :: OS Independent
Classifier: Programming Language :: Python
Classifier: Topic :: Security
Classifier: Topic :: Software Development :: Libraries
